journai/__init__.py
journai/cluster.py
journai/journai.py
journai/map.py
journai/tsp.py
journai_lib-0.1.0.dist-info/LICENSE
journai_lib-0.1.0.dist-info/WHEEL
journai_lib-0.1.0.dist-info/METADATA
journai_lib-0.1.0.dist-info/RECORD
