Metadata-Version: 2.1
Name: journai-lib
Version: 0.1.0
Summary: Let machine learning and operations research plan your next trip.
License: 3-clause BSD license
Author: tlentali
Author-email: thomas.lentali@gmail.com
Requires-Python: >=3.10,<3.12
Classifier: License :: Other/Proprietary License
Classifier: Programming Language :: Python :: 3
Classifier: Programming Language :: Python :: 3.10
Classifier: Programming Language :: Python :: 3.11
Requires-Dist: folium (>=0.14.0,<0.15.0)
Requires-Dist: jupyter (>=1.0.0,<2.0.0)
Requires-Dist: ortools (>=9.6.2534,<10.0.0)
Requires-Dist: pandas (>=2.0.0,<3.0.0)
Requires-Dist: scikit-learn (>=1.2.2,<2.0.0)
